easyvvuq_qcgpj-0.5.3rc15.data/scripts/easyvvuq_encode
easyvvuq_qcgpj-0.5.3rc15.data/scripts/easyvvuq_encode_execute
easyvvuq_qcgpj-0.5.3rc15.data/scripts/easyvvuq_execute
easyvvuq_qcgpj-0.5.3rc15.data/scripts/eqi_utils.sh
eqi/__init__.py
eqi/_version.py
eqi/external_encoder.py
eqi/core/__init__.py
eqi/core/executor.py
eqi/core/processing_scheme.py
eqi/core/resume.py
eqi/core/task.py
eqi/core/task_requirements.py
eqi/core/tasks_manager.py
eqi/utils/__init__.py
eqi/utils/state_keeper.py
easyvvuq_qcgpj-0.5.3rc15.dist-info/LICENSE
easyvvuq_qcgpj-0.5.3rc15.dist-info/METADATA
easyvvuq_qcgpj-0.5.3rc15.dist-info/WHEEL
easyvvuq_qcgpj-0.5.3rc15.dist-info/top_level.txt
easyvvuq_qcgpj-0.5.3rc15.dist-info/RECORD
