Metadata-Version: 2.1
Name: easyvvuq-qcgpj
Version: 0.5.3rc15
Summary: A lightweight plugin for EasyVVUQ enabling the execution of demanding VVUQ procedures using the QCG-PilotJob mechanism.
Home-page: https://github.com/vecma-project/EasyVVUQ-QCGPJ
Author: Bartosz Bosak
License: UNKNOWN
Platform: UNKNOWN
Requires-Dist: pytest
Requires-Dist: pytest-flake8
